LICENSE
MANIFEST.in
README.rst
setup.cfg
setup.py
getolaf.egg-info/PKG-INFO
getolaf.egg-info/SOURCES.txt
getolaf.egg-info/dependency_links.txt
getolaf.egg-info/entry_points.txt
getolaf.egg-info/requires.txt
getolaf.egg-info/top_level.txt
olaf/__init__.py
olaf/app.py
olaf/cli.py
olaf/config-sample.py
olaf/utils.py
olaf/demo-files/hello-world.md
olaf/demo-files/sample-page.md
olaf/demo-files/typography.md
olaf/themes/basic/static/css/main.css
olaf/themes/basic/static/css/normalize.css
olaf/themes/basic/static/css/skeleton.css
olaf/themes/basic/static/css/style.css
olaf/themes/basic/static/img/favicon.png
olaf/themes/basic/static/img/olaf.gif
olaf/themes/basic/static/js/main.js
olaf/themes/basic/static/js/vendor/modernizr-2.6.2.min.js
olaf/themes/basic/templates/404.html
olaf/themes/basic/templates/archive.html
olaf/themes/basic/templates/archive_page.html
olaf/themes/basic/templates/base.html
olaf/themes/basic/templates/content.html
olaf/themes/basic/templates/index.html
olaf/themes/basic/templates/list_pages.html
olaf/themes/basic/templates/list_posts.html
olaf/themes/basic/templates/sitemap.xml
olaf/themes/basic/templates/tag.html
olaf/themes/basic/templates/tags.html
olaf/tools/__init__.py
olaf/tools/create.py
olaf/tools/git.py