Metadata-Version: 1.1
Name: getolaf
Version: 1.0.2
Summary: A static site generator based on flask and markdown
Home-page: https://github.com/vividvilla/olaf
Author: Vivek R
Author-email: vividvilla@gmail.com
License: MIT
Platform: any
Classifier: Framework :: Flask
Classifier: Environment :: Console
Classifier: Environment :: Web Environment
Classifier: License :: OSI Approved :: BSD License
Classifier: Operating System :: OS Independent
Classifier: Programming Language :: Python
Classifier: Programming Language :: Python :: 2.7
Classifier: Topic :: Internet :: WWW/HTTP :: Dynamic Content
